README.md
setup.py
print2slack/__init__.py
print2slack.egg-info/PKG-INFO
print2slack.egg-info/SOURCES.txt
print2slack.egg-info/dependency_links.txt
print2slack.egg-info/top_level.txt