Metadata-Version: 1.0
Name: print2slack
Version: 0.1
Summary: print() to slack!
Home-page: https://github.com/eth0izzle/print2slack
Author: Paul Price
Author-email: paul@ifc0nfig.com
License: MIT
Keywords: slack
Platform: UNKNOWN
